{
    "data": [
      {
        "id": 1,
        "song": "刺猬",
        "src": "https://qq632119185.github.io/hook/static/audio/98759.mp3",
        "singer": "上官婉儿",
        "album": "刺猬",
        "pic": "http://img.5nd.com/photo/2020album/202012/98759.jpg",
        "lrc": [
          {
            "timep": "00:02.84",
            "lrcp": "刺猬"
          },
          {
            "timep": "00:03.38",
            "lrcp": "词：任浩铭"
          },
          {
            "timep": "00:03.70",
            "lrcp": "曲：任浩铭"
          },
          {
            "timep": "00:03.96",
            "lrcp": "编曲：李琳萱"
          },
          {
            "timep": "00:04.20",
            "lrcp": "吉他：陈竹"
          },
          {
            "timep": "00:04.53",
            "lrcp": "录音：祝子由"
          },
          {
            "timep": "00:04.78",
            "lrcp": "和音：雪无影"
          },
          {
            "timep": "00:05.05",
            "lrcp": "混音：大伟"
          },
          {
            "timep": "00:05.36",
            "lrcp": "制作人：薛正一"
          },
          {
            "timep": "00:05.64",
            "lrcp": "OP:Leader Music"
          },
          {
            "timep": "00:05.97",
            "lrcp": "发行公司：百纳娱乐"
          },
          {
            "timep": "00:06.20",
            "lrcp": "制作公司：Leader Music"
          },
          {
            "timep": "00:06.46",
            "lrcp": "出品人：唐岩/王力"
          },
          {
            "timep": "00:06.68",
            "lrcp": "特别出品：AP"
          },
          {
            "timep": "00:07.16",
            "lrcp": "出品：北京陌陌科技有限公司"
          },
          {
            "timep": "00:20.92",
            "lrcp": "看电影伤心了会流泪"
          },
          {
            "timep": "00:25.44",
            "lrcp": "总觉得难过了才算完美"
          },
          {
            "timep": "00:30.81",
            "lrcp": "可是当爱情欺负自己的时候"
          },
          {
            "timep": "00:36.32",
            "lrcp": "才知道那痛苦的滋味"
          },
          {
            "timep": "00:41.07",
            "lrcp": "不想听不想说我好累"
          },
          {
            "timep": "00:45.74",
            "lrcp": "冲一杯咖啡都没了热水"
          },
          {
            "timep": "00:51.19",
            "lrcp": "想对自己说一句"
          },
          {
            "timep": "00:53.88",
            "lrcp": "真的无所谓"
          },
          {
            "timep": "00:56.63",
            "lrcp": "可怜那不争气的眼泪"
          },
          {
            "timep": "01:03.12",
            "lrcp": "我就像受伤的刺猬"
          },
          {
            "timep": "01:06.85",
            "lrcp": "躲进夜的黑"
          },
          {
            "timep": "01:09.07",
            "lrcp": "不敢再放下我的防备"
          },
          {
            "timep": "01:14.62",
            "lrcp": "爱到了悬崖"
          },
          {
            "timep": "01:17.14",
            "lrcp": "如此的卑微"
          },
          {
            "timep": "01:19.29",
            "lrcp": "如果你也不曾后悔"
          },
          {
            "timep": "01:24.25",
            "lrcp": "我就像受伤的刺猬"
          },
          {
            "timep": "01:27.23",
            "lrcp": "天亮了又黑"
          },
          {
            "timep": "01:29.45",
            "lrcp": "劝自己说一句无所谓"
          },
          {
            "timep": "01:35.03",
            "lrcp": "若再爱一回"
          },
          {
            "timep": "01:37.41",
            "lrcp": "谁会记得谁"
          },
          {
            "timep": "01:39.90",
            "lrcp": "给我拥抱"
          },
          {
            "timep": "01:43.91",
            "lrcp": "给我安慰"
          },
          {
            "timep": "02:10.39",
            "lrcp": "不想听不想说我好累"
          },
          {
            "timep": "02:15.20",
            "lrcp": "冲一杯咖啡都没了热水"
          },
          {
            "timep": "02:20.56",
            "lrcp": "想对自己说一句"
          },
          {
            "timep": "02:23.18",
            "lrcp": "真的无所谓"
          },
          {
            "timep": "02:26.04",
            "lrcp": "可怜那不争气的眼泪"
          },
          {
            "timep": "02:32.66",
            "lrcp": "我就像受伤的刺猬"
          },
          {
            "timep": "02:36.17",
            "lrcp": "躲进夜的黑"
          },
          {
            "timep": "02:38.52",
            "lrcp": "不敢再放下我的防备"
          },
          {
            "timep": "02:44.04",
            "lrcp": "爱到了悬崖"
          },
          {
            "timep": "02:46.53",
            "lrcp": "如此的卑微"
          },
          {
            "timep": "02:48.70",
            "lrcp": "如果你也不曾后悔"
          },
          {
            "timep": "02:53.66",
            "lrcp": "我就像受伤的刺猬"
          },
          {
            "timep": "02:56.45",
            "lrcp": "天亮了又黑"
          },
          {
            "timep": "02:58.88",
            "lrcp": "劝自己说一句无所谓"
          },
          {
            "timep": "03:04.33",
            "lrcp": "若再爱一回"
          },
          {
            "timep": "03:06.87",
            "lrcp": "谁会记得谁"
          },
          {
            "timep": "03:09.24",
            "lrcp": "给我拥抱"
          },
          {
            "timep": "03:13.04",
            "lrcp": "给我安慰"
          }
        ],
        "completed": false,
        "paly": false,
        "share": false
      },
      {
        "id": 2,
        "song": "因为爱",
        "src": "https://qq632119185.github.io/hook/static/audio/98808.mp3",
        "singer": "白帆",
        "album": "因为爱",
        "pic": "http://img.5nd.com/photo/2020album/202012/98808.jpg",
        "lrc": [
          {
            "timep": "00:00.53",
            "lrcp": "因为爱"
          },
          {
            "timep": "00:01.10",
            "lrcp": "演唱 Singer：白帆（BAI）"
          },
          {
            "timep": "00:01.14",
            "lrcp": "作词Lyrics：白帆（BAI）/柳李（Atom Panda）"
          },
          {
            "timep": "00:01.29",
            "lrcp": "作曲Composition：白帆（BAI）/柳李（Atom Panda）"
          },
          {
            "timep": "00:02.10",
            "lrcp": "编曲Arranger：柳李（AtomPanda）"
          },
          {
            "timep": "00:03.00",
            "lrcp": "录音Recording：Ultimate Records Studio（上海）"
          },
          {
            "timep": "00:03.89",
            "lrcp": "混音Mix：柳李（Atom Panda）"
          },
          {
            "timep": "00:04.73",
            "lrcp": "制作人Produced By：柳李（Atom Panda）"
          },
          {
            "timep": "00:06.73",
            "lrcp": "发行：杭州回声文化艺术策划有限公司"
          },
          {
            "timep": "00:07.44",
            "lrcp": "迷恋 你的"
          },
          {
            "timep": "00:11.21",
            "lrcp": "每一个微笑"
          },
          {
            "timep": "00:14.98",
            "lrcp": "星空海岛"
          },
          {
            "timep": "00:18.71",
            "lrcp": "一切都刚好"
          },
          {
            "timep": "00:22.53",
            "lrcp": "没有纷扰"
          },
          {
            "timep": "00:25.94",
            "lrcp": "肆意奔跑"
          },
          {
            "timep": "00:29.55",
            "lrcp": "神魂颠倒"
          },
          {
            "timep": "00:32.77",
            "lrcp": "因为爱"
          },
          {
            "timep": "00:37.50",
            "lrcp": "OPEN YOUR EYE"
          },
          {
            "timep": "00:39.82",
            "lrcp": "肩膀为你打开"
          },
          {
            "timep": "00:41.78",
            "lrcp": "因为我 相信爱"
          },
          {
            "timep": "00:45.00",
            "lrcp": "空气暖了起来"
          },
          {
            "timep": "00:46.89",
            "lrcp": "夜空亮了起来"
          },
          {
            "timep": "00:48.78",
            "lrcp": "因为我 相信爱"
          },
          {
            "timep": "00:52.53",
            "lrcp": "喔"
          },
          {
            "timep": "00:55.32",
            "lrcp": "因为爱"
          },
          {
            "timep": "01:00.00",
            "lrcp": "喔"
          },
          {
            "timep": "01:02.75",
            "lrcp": "因为爱"
          },
          {
            "timep": "01:30.04",
            "lrcp": "也许 这是"
          },
          {
            "timep": "01:33.74",
            "lrcp": "命运的安排"
          },
          {
            "timep": "01:37.52",
            "lrcp": "我们 不必"
          },
          {
            "timep": "01:41.25",
            "lrcp": "太大惊小怪"
          },
          {
            "timep": "01:45.00",
            "lrcp": "为你点亮"
          },
          {
            "timep": "01:48.25",
            "lrcp": "每一个晚上"
          },
          {
            "timep": "01:52.35",
            "lrcp": "不会遗忘"
          },
          {
            "timep": "01:55.25",
            "lrcp": "因为爱"
          },
          {
            "timep": "02:00.03",
            "lrcp": "OPEN YOUR EYE"
          },
          {
            "timep": "02:02.34",
            "lrcp": "肩膀为你打开"
          },
          {
            "timep": "02:04.34",
            "lrcp": "因为我 相信爱"
          },
          {
            "timep": "02:07.54",
            "lrcp": "空气暖了起来"
          },
          {
            "timep": "02:09.44",
            "lrcp": "夜空亮了起来"
          },
          {
            "timep": "02:11.71",
            "lrcp": "因为我 相信爱"
          },
          {
            "timep": "02:15.00",
            "lrcp": "喔"
          },
          {
            "timep": "02:17.80",
            "lrcp": "因为爱"
          },
          {
            "timep": "02:22.49",
            "lrcp": "喔"
          },
          {
            "timep": "02:25.30",
            "lrcp": "因为爱"
          },
          {
            "timep": "02:45.05",
            "lrcp": "喔"
          },
          {
            "timep": "02:47.78",
            "lrcp": "因为爱"
          },
          {
            "timep": "02:52.52",
            "lrcp": "喔"
          },
          {
            "timep": "02:55.31",
            "lrcp": "因为爱"
          },
          {
            "timep": "03:00.00",
            "lrcp": "#2020 MONSTER PARTY MUSIC"
          }
        ],
        "completed": false,
        "paly": false,
        "share": false
      },
      {
        "id": 3,
        "song": "你有我就有",
        "src": "https://qq632119185.github.io/hook/static/audio/98799.mp3",
        "singer": "三旺",
        "album": "你有我就有",
        "pic": "http://img.5nd.com/photo/2020album/202012/98799.jpg",
        "lrc": [
          {
            "timep": "00:01.51",
            "lrcp": "你有我就有"
          },
          {
            "timep": "00:02.48",
            "lrcp": "词：三旺、大海"
          },
          {
            "timep": "00:02.94",
            "lrcp": "曲：吴雪松、摇滚君哥"
          },
          {
            "timep": "00:03.40",
            "lrcp": "编曲：陈竹"
          },
          {
            "timep": "00:03.81",
            "lrcp": "制作人：大海@TonewaveMusic"
          },
          {
            "timep": "00:04.21",
            "lrcp": "吉他：陈竹"
          },
          {
            "timep": "00:04.56",
            "lrcp": "贝斯：陈竹"
          },
          {
            "timep": "00:04.92",
            "lrcp": "和声编写：翁倩芸、大海"
          },
          {
            "timep": "00:05.38",
            "lrcp": "和声：翁倩芸、大海"
          },
          {
            "timep": "00:05.89",
            "lrcp": "配唱制作人：大海"
          },
          {
            "timep": "00:06.25",
            "lrcp": "录音：胡春阳"
          },
          {
            "timep": "00:06.60",
            "lrcp": "录音棚：拉近Studio、同为音乐TonewaveMusic"
          },
          {
            "timep": "00:07.02",
            "lrcp": "混音：徐志明"
          },
          {
            "timep": "00:07.43",
            "lrcp": "母带：徐志明"
          },
          {
            "timep": "00:07.83",
            "lrcp": "制作统筹：声音丛林"
          },
          {
            "timep": "00:08.24",
            "lrcp": "出品人：唐岩、王力"
          },
          {
            "timep": "00:08.64",
            "lrcp": "特别出品：旺家军"
          },
          {
            "timep": "00:09.05",
            "lrcp": "出品：北京陌陌科技有限公司"
          },
          {
            "timep": "00:09.57",
            "lrcp": "发行：声音丛林"
          },
          {
            "timep": "00:11.20",
            "lrcp": "酒在杯中 盼望再重逢"
          },
          {
            "timep": "00:15.42",
            "lrcp": "多少往事 沉淀岁月中"
          },
          {
            "timep": "00:19.75",
            "lrcp": "年少的人都喜欢大英雄"
          },
          {
            "timep": "00:24.10",
            "lrcp": "长大以后才知双肩的重"
          },
          {
            "timep": "00:28.57",
            "lrcp": "生活的学问 生活里面懂"
          },
          {
            "timep": "00:32.65",
            "lrcp": "太多儿时梦 在酒后翻涌"
          },
          {
            "timep": "00:37.04",
            "lrcp": "花花的世界 诱惑有百种"
          },
          {
            "timep": "00:41.42",
            "lrcp": "匆忙一生中做黄粱梦"
          },
          {
            "timep": "00:47.76",
            "lrcp": "相逢是杯酒 紧握你的手"
          },
          {
            "timep": "00:53.32",
            "lrcp": "往事历历在 初心不易守"
          },
          {
            "timep": "00:56.84",
            "lrcp": "欲倾肺腑言 感动哽住喉"
          },
          {
            "timep": "01:01.03",
            "lrcp": "快快乐乐过一生"
          },
          {
            "timep": "01:03.62",
            "lrcp": "你有我就有"
          },
          {
            "timep": "01:05.96",
            "lrcp": "干完这杯酒 人散缘还留"
          },
          {
            "timep": "01:09.94",
            "lrcp": "情义比天高 友情暖心头"
          },
          {
            "timep": "01:14.31",
            "lrcp": "无惧风和雨 只愿人长久"
          },
          {
            "timep": "01:18.59",
            "lrcp": "快快乐乐过一生"
          },
          {
            "timep": "01:20.77",
            "lrcp": "你有我就有"
          },
          {
            "timep": "01:31.91",
            "lrcp": "生活的学问 生活里面懂"
          },
          {
            "timep": "01:36.32",
            "lrcp": "太多儿时梦 在酒后翻涌"
          },
          {
            "timep": "01:40.35",
            "lrcp": "花花的世界 诱惑有百种"
          },
          {
            "timep": "01:44.72",
            "lrcp": "匆忙一生中做黄粱梦"
          },
          {
            "timep": "01:51.97",
            "lrcp": "相逢是杯酒 紧握你的手"
          },
          {
            "timep": "01:55.59",
            "lrcp": "往事历历在 初心不易守"
          },
          {
            "timep": "01:59.92",
            "lrcp": "欲倾肺腑言 感动哽住喉"
          },
          {
            "timep": "02:04.15",
            "lrcp": "快快乐乐过一生"
          },
          {
            "timep": "02:06.50",
            "lrcp": "你有我就有"
          },
          {
            "timep": "02:09.31",
            "lrcp": "干完这杯酒 人散缘还留"
          },
          {
            "timep": "02:13.29",
            "lrcp": "情义比天高 友情暖心头"
          },
          {
            "timep": "02:17.45",
            "lrcp": "无惧风和雨 只愿人长久"
          },
          {
            "timep": "02:21.66",
            "lrcp": "快快乐乐过一生"
          },
          {
            "timep": "02:24.10",
            "lrcp": "你有我就有"
          },
          {
            "timep": "02:28.52",
            "lrcp": "相逢是杯酒 紧握你的手"
          },
          {
            "timep": "02:32.88",
            "lrcp": "往事历历在 初心不易守"
          },
          {
            "timep": "02:37.20",
            "lrcp": "欲倾肺腑言 感动哽住喉"
          },
          {
            "timep": "02:41.59",
            "lrcp": "快快乐乐过一生"
          },
          {
            "timep": "02:43.57",
            "lrcp": "你有我就有"
          },
          {
            "timep": "02:46.22",
            "lrcp": "干完这杯酒 人散缘还留"
          },
          {
            "timep": "02:50.00",
            "lrcp": "情义比天高 友情暖心头"
          },
          {
            "timep": "02:54.57",
            "lrcp": "无惧风和雨 只愿人长久"
          },
          {
            "timep": "02:58.73",
            "lrcp": "快快乐乐过一生"
          },
          {
            "timep": "03:00.98",
            "lrcp": "你有我就有"
          },
          {
            "timep": "03:03.38",
            "lrcp": "快快乐乐过一生"
          },
          {
            "timep": "03:05.46",
            "lrcp": "你有我就有"
          }
        ],
        "completed": false,
        "paly": false,
        "share": false
      },
      {
        "id": 4,
        "song": "在这星空之下",
        "src": "https://qq632119185.github.io/hook/static/audio/98869.mp3",
        "singer": "REID伯虎",
        "album": "在这星空之下",
        "pic": "http://img.5nd.com/photo/2020album/202012/98869.jpg",
        "lrc": [
          {
            "timep": "00:04.07",
            "lrcp": "在这星空之下"
          },
          {
            "timep": "00:06.13",
            "lrcp": "作词：叶勇哲"
          },
          {
            "timep": "00:07.45",
            "lrcp": "作曲：叶勇哲"
          },
          {
            "timep": "00:09.16",
            "lrcp": "演唱：REID伯虎"
          },
          {
            "timep": "00:11.01",
            "lrcp": "编曲：陈希阳"
          },
          {
            "timep": "00:13.05",
            "lrcp": "后期：音阅佳"
          },
          {
            "timep": "00:14.76",
            "lrcp": "发行：杭州回声文化艺术策划有限公司"
          },
          {
            "timep": "00:32.88",
            "lrcp": "静静的看"
          },
          {
            "timep": "00:36.32",
            "lrcp": "星空如此绚烂"
          },
          {
            "timep": "00:40.21",
            "lrcp": "微笑浮上脸"
          },
          {
            "timep": "00:42.85",
            "lrcp": "苦弥漫在胸间"
          },
          {
            "timep": "00:46.60",
            "lrcp": "我多想要 随风飘往远方"
          },
          {
            "timep": "00:55.46",
            "lrcp": "想坠入星空 任心去流浪 "
          },
          {
            "timep": "01:01.96",
            "lrcp": "这星空无言"
          },
          {
            "timep": "01:05.23",
            "lrcp": "原谅浮华的世界"
          },
          {
            "timep": "01:09.53",
            "lrcp": "我依然记得"
          },
          {
            "timep": "01:12.64",
            "lrcp": "那些幼稚的誓言"
          },
          {
            "timep": "01:16.81",
            "lrcp": "这世间还有 多少疲倦的双眼"
          },
          {
            "timep": "01:25.09",
            "lrcp": "星空下 梦装饰了夜"
          },
          {
            "timep": "02:01.65",
            "lrcp": "风吹过多少"
          },
          {
            "timep": "02:05.62",
            "lrcp": "同样美的星夜"
          },
          {
            "timep": "02:09.31",
            "lrcp": "陌生的你我"
          },
          {
            "timep": "02:12.09",
            "lrcp": "小心许下心愿"
          },
          {
            "timep": "02:15.77",
            "lrcp": "眉头轻舒 星河多么灿烂"
          },
          {
            "timep": "02:24.68",
            "lrcp": "想像中的我 扬着帆远航"
          },
          {
            "timep": "02:31.21",
            "lrcp": "这星空无言"
          },
          {
            "timep": "02:34.43",
            "lrcp": "原谅浮华的世界"
          },
          {
            "timep": "02:38.75",
            "lrcp": "我依然记得"
          },
          {
            "timep": "02:41.87",
            "lrcp": "那些幼稚的誓言"
          },
          {
            "timep": "02:46.06",
            "lrcp": "这世间还有 多少疲倦的双眼"
          },
          {
            "timep": "02:54.32",
            "lrcp": "星空下 梦装饰了夜"
          },
          {
            "timep": "02:57.68",
            "lrcp": "这星光点点"
          },
          {
            "timep": "03:00.56",
            "lrcp": "点亮一人的世界"
          },
          {
            "timep": "03:04.84",
            "lrcp": "我已经遗散"
          },
          {
            "timep": "03:08.02",
            "lrcp": "那些固执的想念"
          },
          {
            "timep": "03:12.12",
            "lrcp": "这世间还有 多少无奈的离别"
          },
          {
            "timep": "03:20.40",
            "lrcp": "星空下 泪润湿了夜"
          },
          {
            "timep": "03:27.62",
            "lrcp": "哦～"
          },
          {
            "timep": "03:30.90",
            "lrcp": "泪落星夜"
          },
          {
            "timep": "03:39.75",
            "lrcp": "那些逝去"
          },
          {
            "timep": "03:41.50",
            "lrcp": "已经化作"
          },
          {
            "timep": "03:43.37",
            "lrcp": "繁星映照漫天"
          },
          {
            "timep": "03:49.56",
            "lrcp": "我在星空之下"
          }
        ],
        "completed": false,
        "paly": false,
        "share": false
      },
      {
        "id": 5,
        "song": "哈尼",
        "src": "https://qq632119185.github.io/hook/static/audio/98646.mp3",
        "singer": "小乐乐",
        "album": "哈尼",
        "pic": "http://img.5nd.com/photo/2020album/202012/98646.jpg",
        "lrc": [
          {
            "timep": "00:03.48",
            "lrcp": "哈尼"
          },
          {
            "timep": "00:04.12",
            "lrcp": "词：风恒成"
          },
          {
            "timep": "00:04.40",
            "lrcp": "曲：赖奕宾 "
          },
          {
            "timep": "00:04.68",
            "lrcp": "编曲：任永恒"
          },
          {
            "timep": "00:05.00",
            "lrcp": "吉他：杨春"
          },
          {
            "timep": "00:05.37",
            "lrcp": "录音：祝子由"
          },
          {
            "timep": "00:05.71",
            "lrcp": "和音：雪无影"
          },
          {
            "timep": "00:05.96",
            "lrcp": "混音：路大伟"
          },
          {
            "timep": "00:06.27",
            "lrcp": "制作人：韩俊平"
          },
          {
            "timep": "00:06.58",
            "lrcp": "OP:Leader Music"
          },
          {
            "timep": "00:06.94",
            "lrcp": "发行公司：百纳娱乐"
          },
          {
            "timep": "00:07.31",
            "lrcp": "制作公司：Leader Music"
          },
          {
            "timep": "00:07.82",
            "lrcp": "出品人：唐岩/王力"
          },
          {
            "timep": "00:08.28",
            "lrcp": "特别出品人：森林"
          },
          {
            "timep": "00:08.85",
            "lrcp": "出品：北京陌陌科技有限公司"
          },
          {
            "timep": "00:18.52",
            "lrcp": "哈尼 我的心已经为你一字排开"
          },
          {
            "timep": "00:24.55",
            "lrcp": "你什么时候到我心里参观"
          },
          {
            "timep": "00:28.73",
            "lrcp": "那朵娇羞 渴望的被爱"
          },
          {
            "timep": "00:32.71",
            "lrcp": "在等你将它暖成花海"
          },
          {
            "timep": "00:35.42",
            "lrcp": "哈尼 我世界就像一座博物馆"
          },
          {
            "timep": "00:41.49",
            "lrcp": "你何时将我神秘的爱解开"
          },
          {
            "timep": "00:45.50",
            "lrcp": "那卷骚动很含蓄的乱"
          },
          {
            "timep": "00:49.54",
            "lrcp": "在等你亲口专业评判"
          },
          {
            "timep": "00:52.08",
            "lrcp": "我好奇你太怪怪"
          },
          {
            "timep": "00:54.12",
            "lrcp": "好奇迷之一坏"
          },
          {
            "timep": "00:56.29",
            "lrcp": "喜欢你对感情　 "
          },
          {
            "timep": "00:58.36",
            "lrcp": "描着蓝图未来"
          },
          {
            "timep": "01:00.43",
            "lrcp": "也喜欢你坦坦荡荡　 "
          },
          {
            "timep": "01:04.77",
            "lrcp": "爱与不爱"
          },
          {
            "timep": "01:06.83",
            "lrcp": "都很坦白"
          },
          {
            "timep": "01:08.91",
            "lrcp": "我好奇 你很呆呆"
          },
          {
            "timep": "01:10.99",
            "lrcp": "好奇像个怪胎"
          },
          {
            "timep": "01:13.23",
            "lrcp": "喜欢你与世俗　"
          },
          {
            "timep": "01:15.16",
            "lrcp": "格格不入例外"
          },
          {
            "timep": "01:17.41",
            "lrcp": "也喜欢你疯狂 "
          },
          {
            "timep": "01:19.74",
            "lrcp": "也像个小孩 "
          },
          {
            "timep": "01:21.90",
            "lrcp": "对事情认真的帅"
          },
          {
            "timep": "01:42.74",
            "lrcp": "哈尼 我的心已经为你一字排开"
          },
          {
            "timep": "01:48.98",
            "lrcp": "你什么时候到我心里参观"
          },
          {
            "timep": "01:52.92",
            "lrcp": "那朵娇羞 渴望的被爱"
          },
          {
            "timep": "01:56.96",
            "lrcp": "在等你将它暖成花海"
          },
          {
            "timep": "01:59.62",
            "lrcp": "哈尼 我世界就像一座博物馆"
          },
          {
            "timep": "02:05.69",
            "lrcp": "你何时将我神秘的爱解开"
          },
          {
            "timep": "02:09.76",
            "lrcp": "那卷骚动很含蓄的乱"
          },
          {
            "timep": "02:13.76",
            "lrcp": "在等你亲口专业评判"
          },
          {
            "timep": "02:16.27",
            "lrcp": "我好奇你太怪怪"
          },
          {
            "timep": "02:18.34",
            "lrcp": "好奇迷之一坏"
          },
          {
            "timep": "02:20.55",
            "lrcp": "喜欢你对感情　 "
          },
          {
            "timep": "02:22.64",
            "lrcp": "描着蓝图未来"
          },
          {
            "timep": "02:24.65",
            "lrcp": "也喜欢你坦坦荡荡　 "
          },
          {
            "timep": "02:28.96",
            "lrcp": "爱与不爱"
          },
          {
            "timep": "02:30.16",
            "lrcp": "都很坦白"
          },
          {
            "timep": "02:33.11",
            "lrcp": "我好奇 你很呆呆"
          },
          {
            "timep": "02:35.23",
            "lrcp": "好奇像个怪胎"
          },
          {
            "timep": "02:37.38",
            "lrcp": "喜欢你与世俗　"
          },
          {
            "timep": "02:39.51",
            "lrcp": "格格不入例外"
          },
          {
            "timep": "02:41.73",
            "lrcp": "也喜欢你疯狂 "
          },
          {
            "timep": "02:44.03",
            "lrcp": "也像个小孩 "
          },
          {
            "timep": "02:46.11",
            "lrcp": "对事情认真的帅"
          },
          {
            "timep": "02:49.93",
            "lrcp": "我好奇 你很呆呆"
          },
          {
            "timep": "02:52.08",
            "lrcp": "好奇像个怪胎"
          },
          {
            "timep": "02:54.23",
            "lrcp": "喜欢你与世俗　"
          },
          {
            "timep": "02:56.33",
            "lrcp": "格格不入例外"
          },
          {
            "timep": "02:58.44",
            "lrcp": "也喜欢你疯狂 "
          },
          {
            "timep": "03:00.92",
            "lrcp": "也像个小孩 "
          },
          {
            "timep": "03:02.90",
            "lrcp": "对事情认真的帅"
          }
        ],
        "completed": false,
        "paly": false,
        "share": false
      },
      {
        "id": 6,
        "song": "缘续（电影《真假美猴王之大圣无双》主题曲）",
        "src": "https://qq632119185.github.io/hook/static/audio/98703.mp3",
        "singer": "赵方婧",
        "album": "缘续",
        "pic": "http://img.5nd.com/photo/2020album/202012/98703.jpg",
        "lrc": [
          {
            "timep": "00:00.540",
            "lrcp": "缘续（电影《真假美猴王之大圣无双》主题曲）"
          },
          {
            "timep": "00:01.097",
            "lrcp": "作词：王瑞淇"
          },
          {
            "timep": "00:01.524",
            "lrcp": "作曲：潘成"
          },
          {
            "timep": "00:01.949",
            "lrcp": "演唱：赵方婧"
          },
          {
            "timep": "00:02.451",
            "lrcp": "制作人：王伊锋"
          },
          {
            "timep": "00:03.026",
            "lrcp": "编曲：卡其漠罗洋"
          },
          {
            "timep": "00:03.467",
            "lrcp": "电木吉他：菇时同学"
          },
          {
            "timep": "00:03.897",
            "lrcp": "二胡：二胡妹"
          },
          {
            "timep": "00:04.280",
            "lrcp": "曲笛梆笛萧：囚牛"
          },
          {
            "timep": "00:04.649",
            "lrcp": "混音：张赫栩"
          },
          {
            "timep": "00:04.952",
            "lrcp": "音乐营销：百态文化"
          },
          {
            "timep": "00:05.398",
            "lrcp": "OP：百态文化"
          },
          {
            "timep": "00:33.585",
            "lrcp": "七彩云霞飞舞 的彩蝶"
          },
          {
            "timep": "00:40.715",
            "lrcp": "捎来耳边软语 落人间"
          },
          {
            "timep": "00:47.414",
            "lrcp": "想把前世谜语 都破解"
          },
          {
            "timep": "00:53.664",
            "lrcp": "却不堪 忍受着 红尘劫"
          },
          {
            "timep": "01:01.968",
            "lrcp": "苍穹之上的美梦 百日久"
          },
          {
            "timep": "01:08.868",
            "lrcp": "化作人间的烟火 飘零落"
          },
          {
            "timep": "01:15.700",
            "lrcp": "零星散落的魂魄 挂长空"
          },
          {
            "timep": "01:21.523",
            "lrcp": "真的心 真的魂 过这生"
          },
          {
            "timep": "01:27.207",
            "lrcp": "执念此情 不惜一切 赴万里"
          },
          {
            "timep": "01:34.747",
            "lrcp": "不远万里 上天入地 找寻你"
          },
          {
            "timep": "01:41.513",
            "lrcp": "不问归期何许"
          },
          {
            "timep": "01:45.255",
            "lrcp": "不闻岁月何语"
          },
          {
            "timep": "01:48.350",
            "lrcp": "只若星陨落 缘续你"
          },
          {
            "timep": "02:27.292",
            "lrcp": "七彩云霞飞舞 的彩蝶"
          },
          {
            "timep": "02:33.763",
            "lrcp": "捎来耳边软语 落人间"
          },
          {
            "timep": "02:40.447",
            "lrcp": "想把前世谜语 都破解"
          },
          {
            "timep": "02:46.721",
            "lrcp": "却不堪 忍受着 红尘劫"
          },
          {
            "timep": "02:55.062",
            "lrcp": "苍穹之上的美梦 百日久"
          },
          {
            "timep": "03:02.265",
            "lrcp": "化作人间的烟火 飘零落"
          },
          {
            "timep": "03:09.232",
            "lrcp": "零星散落的魂魄 挂长空"
          },
          {
            "timep": "03:14.574",
            "lrcp": "真的心 真的魂 过这生"
          },
          {
            "timep": "03:20.314",
            "lrcp": "执念此情 不惜一切 赴万里"
          },
          {
            "timep": "03:27.142",
            "lrcp": "不远万里 上天入地 找寻你"
          },
          {
            "timep": "03:34.373",
            "lrcp": "不问归期何许"
          },
          {
            "timep": "03:37.858",
            "lrcp": "不闻岁月何语"
          },
          {
            "timep": "03:41.459",
            "lrcp": "只若星陨落 缘续你"
          },
          {
            "timep": "03:48.363",
            "lrcp": "执念此情 不惜一切 赴万里"
          },
          {
            "timep": "03:54.672",
            "lrcp": "不远万里 上天入地 找寻你"
          },
          {
            "timep": "04:01.852",
            "lrcp": "不问归期何许"
          },
          {
            "timep": "04:05.396",
            "lrcp": "不闻岁月何语"
          },
          {
            "timep": "04:08.780",
            "lrcp": "只若星陨落 缘续你"
          }
        ],
        "completed": false,
        "paly": false,
        "share": false
      },
      {
        "id": 7,
        "song": "小气",
        "src": "https://qq632119185.github.io/hook/static/audio/98622.mp3",
        "singer": "艺宝宝（权艺）",
        "album": "小气",
        "pic": "http://img.5nd.com/photo/2020album/202011/98622.jpg",
        "lrc": [
          {
            "timep": "00:02.12",
            "lrcp": "小气"
          },
          {
            "timep": "00:02.97",
            "lrcp": "演唱：艺宝宝（权艺）、小峰峰（陈峰）"
          },
          {
            "timep": "00:03.35",
            "lrcp": "作词：小峰峰（陈峰）"
          },
          {
            "timep": "00:03.73",
            "lrcp": "作曲：小峰峰（陈峰）"
          },
          {
            "timep": "00:04.09",
            "lrcp": "编曲：恩德Andy18"
          },
          {
            "timep": "00:04.45",
            "lrcp": "制作人：小峰峰（陈峰）"
          },
          {
            "timep": "00:04.73",
            "lrcp": "吉他：韩俊平"
          },
          {
            "timep": "00:05.09",
            "lrcp": "配唱制作人：小峰峰（陈峰）"
          },
          {
            "timep": "00:05.33",
            "lrcp": "和声：小峰峰（陈峰）、曾婕Joey.Z"
          },
          {
            "timep": "00:05.68",
            "lrcp": "混音：陈秋洁"
          },
          {
            "timep": "00:06.00",
            "lrcp": "监制：小峰峰（陈峰）"
          },
          {
            "timep": "00:06.30",
            "lrcp": "发行：百纳娱乐"
          },
          {
            "timep": "00:06.67",
            "lrcp": "出品人：唐岩、王力"
          },
          {
            "timep": "00:06.98",
            "lrcp": "特别出品：点点"
          },
          {
            "timep": "00:07.37",
            "lrcp": "出品：北京陌陌科技有限公司"
          },
          {
            "timep": "00:10.21",
            "lrcp": "女："
          },
          {
            "timep": "00:10.58",
            "lrcp": "你不要生气"
          },
          {
            "timep": "00:12.21",
            "lrcp": "快看我的眼睛"
          },
          {
            "timep": "00:14.37",
            "lrcp": "哄哄你的心情"
          },
          {
            "timep": "00:16.60",
            "lrcp": "我逗你开心"
          },
          {
            "timep": "00:19.12",
            "lrcp": "你这么小气"
          },
          {
            "timep": "00:21.05",
            "lrcp": "摸摸你的良心"
          },
          {
            "timep": "00:23.20",
            "lrcp": "强大的占有欲"
          },
          {
            "timep": "00:25.41",
            "lrcp": "满满的醋意"
          },
          {
            "timep": "00:29.04",
            "lrcp": "整个晚上都睡不着"
          },
          {
            "timep": "00:33.45",
            "lrcp": "月亮也变得不圆了"
          },
          {
            "timep": "00:37.93",
            "lrcp": "好怀念幸福时刻的拥抱"
          },
          {
            "timep": "00:41.16",
            "lrcp": "可你的小孩气乱吃醋也让我快疯掉"
          },
          {
            "timep": "00:46.78",
            "lrcp": "好希望你我之间 一直都没有秘密"
          },
          {
            "timep": "00:51.08",
            "lrcp": "好希望我们关系 在一起时越来越亲密"
          },
          {
            "timep": "00:55.57",
            "lrcp": "好希望你别再 别再那么小孩气"
          },
          {
            "timep": "00:59.85",
            "lrcp": "好好跟你沟通"
          },
          {
            "timep": "01:01.77",
            "lrcp": "怎么没有用"
          },
          {
            "timep": "01:03.34",
            "lrcp": "你不要生气"
          },
          {
            "timep": "01:04.98",
            "lrcp": "快看我的眼睛"
          },
          {
            "timep": "01:07.19",
            "lrcp": "哄哄你的心情"
          },
          {
            "timep": "01:09.49",
            "lrcp": "我逗你开心"
          },
          {
            "timep": "01:10.09",
            "lrcp": "　　"
          },
          {
            "timep": "01:12.02",
            "lrcp": "你这么小气"
          },
          {
            "timep": "01:13.79",
            "lrcp": "摸摸你的良心"
          },
          {
            "timep": "01:15.98",
            "lrcp": "强大的占有欲"
          },
          {
            "timep": "01:18.41",
            "lrcp": "满满的醋意"
          },
          {
            "timep": "01:20.57",
            "lrcp": "别这么小气"
          },
          {
            "timep": "01:21.60",
            "lrcp": "男RAP:"
          },
          {
            "timep": "01:30.42",
            "lrcp": "你也知道我也睡不着"
          },
          {
            "timep": "01:32.47",
            "lrcp": "面前的夜宵突然就不香了"
          },
          {
            "timep": "01:35.05",
            "lrcp": "你不在的时候真 难熬"
          },
          {
            "timep": "01:37.21",
            "lrcp": "对不起我不该对你大吼大叫"
          },
          {
            "timep": "01:39.22",
            "lrcp": "你不在的时候我像得重感冒"
          },
          {
            "timep": "01:41.49",
            "lrcp": "你的温柔就是　苦口良药 "
          },
          {
            "timep": "01:43.91",
            "lrcp": "看不见你 我又想你"
          },
          {
            "timep": "01:45.93",
            "lrcp": "我会试着改变"
          },
          {
            "timep": "01:46.96",
            "lrcp": "去改变我的脾气"
          },
          {
            "timep": "01:48.01",
            "lrcp": "女："
          },
          {
            "timep": "01:48.57",
            "lrcp": "整个晚上都睡不着（男：睡不着睡不着怎么办啊）"
          },
          {
            "timep": "01:52.68",
            "lrcp": "月亮也变得不圆了（男：没你在月亮没有那么圆了）"
          },
          {
            "timep": "01:57.15",
            "lrcp": "好怀念幸福时刻的拥抱"
          },
          {
            "timep": "02:00.37",
            "lrcp": "可你的小孩气乱吃醋也让我快疯掉"
          },
          {
            "timep": "02:06.06",
            "lrcp": "好希望你我之间 一直都没有秘密"
          },
          {
            "timep": "02:10.29",
            "lrcp": "好希望我们关系 在一起时越来越亲密"
          },
          {
            "timep": "02:14.85",
            "lrcp": "好希望你别再 别再那么小孩气"
          },
          {
            "timep": "02:19.12",
            "lrcp": "好想跟你牵手"
          },
          {
            "timep": "02:21.09",
            "lrcp": "一直到白头"
          },
          {
            "timep": "02:22.57",
            "lrcp": "你不要生气"
          },
          {
            "timep": "02:24.44",
            "lrcp": "快看我的眼睛"
          },
          {
            "timep": "02:26.45",
            "lrcp": "哄哄你的心情"
          },
          {
            "timep": "02:28.68",
            "lrcp": "我逗你开心"
          },
          {
            "timep": "02:29.33",
            "lrcp": "　　"
          },
          {
            "timep": "02:31.25",
            "lrcp": "你这么小气"
          },
          {
            "timep": "02:33.05",
            "lrcp": "摸摸你的良心"
          },
          {
            "timep": "02:35.29",
            "lrcp": "强大的占有欲"
          },
          {
            "timep": "02:37.53",
            "lrcp": "满满的醋意"
          },
          {
            "timep": "02:39.77",
            "lrcp": "别这么小气"
          },
          {
            "timep": "02:40.74",
            "lrcp": "男RAP："
          },
          {
            "timep": "02:41.37",
            "lrcp": "不懂 我还是不懂"
          },
          {
            "timep": "02:42.79",
            "lrcp": "越来越喜欢你我就会变得像个女生"
          },
          {
            "timep": "02:45.21",
            "lrcp": "胡思乱想的我 你对我太高冷"
          },
          {
            "timep": "02:47.22",
            "lrcp": "缺少沟通 闷在心里开始怀疑人生 "
          },
          {
            "timep": "02:49.65",
            "lrcp": "倔强 谁比谁倔强"
          },
          {
            "timep": "02:51.58",
            "lrcp": "我是个男生是我的错不该总是这样"
          },
          {
            "timep": "02:54.01",
            "lrcp": "只因在乎对方 才像小孩一样"
          },
          {
            "timep": "02:54.97",
            "lrcp": "像小气鬼要强"
          },
          {
            "timep": "02:57.63",
            "lrcp": "女："
          },
          {
            "timep": "02:58.05",
            "lrcp": "你不要生气"
          },
          {
            "timep": "02:59.62",
            "lrcp": "快看我的眼睛"
          },
          {
            "timep": "03:01.74",
            "lrcp": "哄哄你的心情"
          },
          {
            "timep": "03:04.01",
            "lrcp": "我逗你开心"
          },
          {
            "timep": "03:04.54",
            "lrcp": "　　"
          },
          {
            "timep": "03:06.52",
            "lrcp": "你这么小气"
          },
          {
            "timep": "03:08.37",
            "lrcp": "摸摸你的良心"
          },
          {
            "timep": "03:10.54",
            "lrcp": "强大的占有欲"
          },
          {
            "timep": "03:12.73",
            "lrcp": "满满的醋意"
          },
          {
            "timep": "03:15.31",
            "lrcp": "你不要生气"
          },
          {
            "timep": "03:17.13",
            "lrcp": "快看我的眼睛"
          },
          {
            "timep": "03:19.40",
            "lrcp": "哄哄你的心情"
          },
          {
            "timep": "03:21.58",
            "lrcp": "我逗你开心"
          },
          {
            "timep": "03:22.29",
            "lrcp": "　　"
          },
          {
            "timep": "03:24.05",
            "lrcp": "你这么小气"
          },
          {
            "timep": "03:25.91",
            "lrcp": "摸摸你的良心"
          },
          {
            "timep": "03:28.11",
            "lrcp": "强大的占有欲"
          },
          {
            "timep": "03:30.41",
            "lrcp": "满满的醋意"
          },
          {
            "timep": "03:32.57",
            "lrcp": "别这么小气"
          }
        ],
        "completed": false,
        "paly": false,
        "share": false
      },
      {
        "id": 8,
        "song": "远山的宝藏",
        "src": "https://qq632119185.github.io/hook/static/audio/98578.mp3",
        "singer": "三木科",
        "album": "远山的宝藏",
        "pic": "http://img.5nd.com/photo/2020album/202011/98578.jpg",
        "lrc": [
          {
            "timep": "00:00.00",
            "lrcp": "三木科-远山的宝藏"
          },
          {
            "timep": "00:03.00",
            "lrcp": "作词：G_10"
          },
          {
            "timep": "00:06.00",
            "lrcp": "作曲：AntChannel_陈超"
          },
          {
            "timep": "00:20.48",
            "lrcp": "和白云飞过山巅"
          },
          {
            "timep": "00:22.94",
            "lrcp": "落进孩子们的清澈双眼"
          },
          {
            "timep": "00:25.19",
            "lrcp": "像是一种古老语言"
          },
          {
            "timep": "00:27.40",
            "lrcp": "翻译着碧湖和蓝天"
          },
          {
            "timep": "00:29.69",
            "lrcp": "站在了起跑线"
          },
          {
            "timep": "00:31.84",
            "lrcp": "没有任何人能提前遇见"
          },
          {
            "timep": "00:34.49",
            "lrcp": "或深渊 或冒险"
          },
          {
            "timep": "00:36.50",
            "lrcp": "跑着不让梦搁浅"
          },
          {
            "timep": "00:38.81",
            "lrcp": "路 远方的路"
          },
          {
            "timep": "00:41.14",
            "lrcp": "体会时间像一场魔术"
          },
          {
            "timep": "00:43.50",
            "lrcp": "远山的风"
          },
          {
            "timep": "00:45.84",
            "lrcp": "寻心中永恒的深处"
          },
          {
            "timep": "00:48.69",
            "lrcp": "不怕输 用冰雪领悟"
          },
          {
            "timep": "00:50.86",
            "lrcp": "坚定向前内心热力温度"
          },
          {
            "timep": "00:53.04",
            "lrcp": "将沿途风景收入囊中"
          },
          {
            "timep": "00:55.47",
            "lrcp": "落笔在天际线"
          },
          {
            "timep": "00:58.32",
            "lrcp": "????????????????"
          },
          {
            "timep": "01:00.59",
            "lrcp": "远方的路"
          },
          {
            "timep": "01:02.59",
            "lrcp": "???????????????"
          },
          {
            "timep": "01:04.99",
            "lrcp": "不管多远"
          },
          {
            "timep": "01:06.99",
            "lrcp": "?????????????"
          },
          {
            "timep": "01:09.48",
            "lrcp": "年轻一代"
          },
          {
            "timep": "01:11.48",
            "lrcp": "???????????????"
          },
          {
            "timep": "01:13.48",
            "lrcp": "勿失自道"
          },
          {
            "timep": "01:16.55",
            "lrcp": "啊 隐约听见你的呼吸"
          },
          {
            "timep": "01:23.62",
            "lrcp": "进入圣殿后打开新世界"
          },
          {
            "timep": "01:28.06",
            "lrcp": "让我连接远处每一道光"
          },
          {
            "timep": "01:37.26",
            "lrcp": "和白云飞过山巅"
          },
          {
            "timep": "01:39.17",
            "lrcp": "落进孩子们的清澈双眼"
          },
          {
            "timep": "01:41.38",
            "lrcp": "像是一种古老语言"
          },
          {
            "timep": "01:43.64",
            "lrcp": "翻译着碧湖和蓝天"
          },
          {
            "timep": "01:45.98",
            "lrcp": "站在了起跑线"
          },
          {
            "timep": "01:48.20",
            "lrcp": "没有任何人能提前遇见"
          },
          {
            "timep": "01:50.68",
            "lrcp": "或深渊 或冒险"
          },
          {
            "timep": "01:52.59",
            "lrcp": "跑着不让梦搁浅"
          },
          {
            "timep": "01:54.86",
            "lrcp": "路 远方的路"
          },
          {
            "timep": "01:57.39",
            "lrcp": "体会时间像一场魔术"
          },
          {
            "timep": "01:59.42",
            "lrcp": "远山的风"
          },
          {
            "timep": "02:01.89",
            "lrcp": "寻心中永恒的深处"
          },
          {
            "timep": "02:04.79",
            "lrcp": "不怕输 用冰雪领悟"
          },
          {
            "timep": "02:06.64",
            "lrcp": "坚定向前内心热力温度"
          },
          {
            "timep": "02:09.01",
            "lrcp": "将沿途风景收入囊中"
          },
          {
            "timep": "02:11.52",
            "lrcp": "落笔在天际线"
          },
          {
            "timep": "02:15.00",
            "lrcp": "????????????????"
          },
          {
            "timep": "02:17.00",
            "lrcp": "远方的路"
          },
          {
            "timep": "02:18.51",
            "lrcp": "???????????????"
          },
          {
            "timep": "02:20.56",
            "lrcp": "不管多远"
          },
          {
            "timep": "02:22.56",
            "lrcp": "?????????????"
          },
          {
            "timep": "02:25.62",
            "lrcp": "年轻一代"
          },
          {
            "timep": "02:27.62",
            "lrcp": "???????????????"
          },
          {
            "timep": "02:29.62",
            "lrcp": "勿失自道"
          },
          {
            "timep": "02:32.56",
            "lrcp": "????????????????"
          },
          {
            "timep": "02:35.99",
            "lrcp": "远方的路"
          },
          {
            "timep": "02:36.99",
            "lrcp": "???????????????"
          },
          {
            "timep": "02:39.54",
            "lrcp": "不管多远"
          },
          {
            "timep": "02:41.54",
            "lrcp": "?????????????"
          },
          {
            "timep": "02:43.25",
            "lrcp": "年轻一代"
          },
          {
            "timep": "02:46.25",
            "lrcp": "???????????????"
          },
          {
            "timep": "02:47.33",
            "lrcp": "勿失自道"
          },
          {
            "timep": "02:48.91",
            "lrcp": "?????????????????????????????"
          },
          {
            "timep": "02:50.41",
            "lrcp": "勿忘最初的梦想"
          },
          {
            "timep": "02:51.41",
            "lrcp": "????????????????"
          },
          {
            "timep": "02:53.21",
            "lrcp": "远方的路"
          },
          {
            "timep": "02:55.21",
            "lrcp": "???????????????"
          },
          {
            "timep": "02:58.21",
            "lrcp": "不管多远"
          },
          {
            "timep": "03:00.04",
            "lrcp": "?????????????"
          },
          {
            "timep": "03:02.68",
            "lrcp": "年轻一代"
          },
          {
            "timep": "03:04.68",
            "lrcp": "???????????????"
          },
          {
            "timep": "03:06.68",
            "lrcp": "勿失自道"
          }
        ],
        "completed": false,
        "paly": false,
        "share": false
      },
      {
        "id": 9,
        "song": "趁热",
        "src": "https://qq632119185.github.io/hook/static/audio/98415.mp3",
        "singer": "曹翟",
        "album": "趁热",
        "pic": "http://img.5nd.com/photo/2020album/202011/98415.jpg",
        "lrc": [
          {
            "timep": "00:02.312",
            "lrcp": "趁热"
          },
          {
            "timep": "00:04.412",
            "lrcp": "作词：曹翟 "
          },
          {
            "timep": "00:05.665",
            "lrcp": "作曲：曹翟 "
          },
          {
            "timep": "00:07.169",
            "lrcp": "编曲：曹翟 "
          },
          {
            "timep": "00:08.673",
            "lrcp": "演唱：曹翟 "
          },
          {
            "timep": "00:09.415",
            "lrcp": "和声：徐天晓 "
          },
          {
            "timep": "00:10.428",
            "lrcp": "录音：徐天晓 @ Orange Dreamon Studio"
          },
          {
            "timep": "00:11.681",
            "lrcp": "混音：徐天晓 @ Orange Dreamon Studio "
          },
          {
            "timep": "00:12.671",
            "lrcp": "发行：杭州回声文化艺术策划有限公司"
          },
          {
            "timep": "00:13.436",
            "lrcp": "让最炙烈的阳光给一切充电 "
          },
          {
            "timep": "00:16.444",
            "lrcp": "瞬间能量无限 "
          },
          {
            "timep": "00:19.201",
            "lrcp": "娇气呆在屋里佛系全靠边 "
          },
          {
            "timep": "00:22.458",
            "lrcp": "此刻热情最耀眼 "
          },
          {
            "timep": "00:25.214",
            "lrcp": "把上万吨的汗水蒸发到天边 "
          },
          {
            "timep": "00:28.221",
            "lrcp": "期待彩虹出现 "
          },
          {
            "timep": "00:31.228",
            "lrcp": "谁不渴望一场华丽的冒险 "
          },
          {
            "timep": "00:34.236",
            "lrcp": "寻找新的沸点 "
          },
          {
            "timep": "00:38.748",
            "lrcp": "趁热 去感受 去发现 "
          },
          {
            "timep": "00:41.756",
            "lrcp": "去创造梦中乐园 "
          },
          {
            "timep": "00:44.764",
            "lrcp": "趁热打铁才可能成功 "
          },
          {
            "timep": "00:47.772",
            "lrcp": "无惧坎坷和艰险 "
          },
          {
            "timep": "00:50.780",
            "lrcp": "趁热 去爱吧 去体验 "
          },
          {
            "timep": "00:53.537",
            "lrcp": "去主宰一马当先 "
          },
          {
            "timep": "00:56.796",
            "lrcp": "趁热 越热越爱走出去 "
          },
          {
            "timep": "00:59.801",
            "lrcp": "奔跑起飞 摸得到天 "
          },
          {
            "timep": "01:08.825",
            "lrcp": "让最炙烈的阳光给一切充电 "
          },
          {
            "timep": "01:11.833",
            "lrcp": "瞬间能量无限"
          },
          {
            "timep": "01:14.840",
            "lrcp": "娇气呆在屋里佛系全靠边 "
          },
          {
            "timep": "01:17.847",
            "lrcp": "此刻热情最耀眼 "
          },
          {
            "timep": "01:20.854",
            "lrcp": "把上万吨的汗水蒸发到天边 "
          },
          {
            "timep": "01:23.862",
            "lrcp": "期待彩虹出现 "
          },
          {
            "timep": "01:26.868",
            "lrcp": "谁不渴望一场华丽的冒险 "
          },
          {
            "timep": "01:29.876",
            "lrcp": "寻找新的沸点 "
          },
          {
            "timep": "01:34.388",
            "lrcp": "趁热 去感受 去发现"
          },
          {
            "timep": "01:37.396",
            "lrcp": "去创造梦中乐园 "
          },
          {
            "timep": "01:40.404",
            "lrcp": "趁热打铁才可能成功"
          },
          {
            "timep": "01:43.412",
            "lrcp": "无惧坎坷和艰险 "
          },
          {
            "timep": "01:46.169",
            "lrcp": "趁热 去爱吧 去体验"
          },
          {
            "timep": "01:49.428",
            "lrcp": "去主宰一马当先 "
          },
          {
            "timep": "01:52.436",
            "lrcp": "趁热 越热越爱走出去 "
          },
          {
            "timep": "01:55.444",
            "lrcp": "奔跑起飞 "
          },
          {
            "timep": "01:58.452",
            "lrcp": "趁热 去感受 去发现"
          },
          {
            "timep": "02:01.460",
            "lrcp": "去创造梦中乐园 "
          },
          {
            "timep": "02:04.468",
            "lrcp": "趁热打铁才可能成功 "
          },
          {
            "timep": "02:07.476",
            "lrcp": "无惧坎坷和艰险 "
          },
          {
            "timep": "02:10.234",
            "lrcp": "趁热 去爱吧 去体验 "
          },
          {
            "timep": "02:13.491",
            "lrcp": "去主宰一马当先 "
          },
          {
            "timep": "02:16.497",
            "lrcp": "趁热 越热越爱走出去 "
          },
          {
            "timep": "02:19.505",
            "lrcp": "奔跑起飞 摸得到天"
          }
        ],
        "completed": false,
        "paly": false,
        "share": false
      },
      {
        "id": 10,
        "song": "放开一切去爱吧",
        "src": "https://qq632119185.github.io/hook/static/audio/98508.mp3",
        "singer": "任浩铭",
        "album": "放开一切去爱吧",
        "pic": "http://img.5nd.com/photo/2020album/202011/98508.jpg",
        "lrc": [
          {
            "timep": "00:02.44",
            "lrcp": "放开一切去爱吧"
          },
          {
            "timep": "00:03.56",
            "lrcp": "作词：任浩铭"
          },
          {
            "timep": "00:04.08",
            "lrcp": "作曲：任浩铭"
          },
          {
            "timep": "00:04.56",
            "lrcp": "演唱：慕容晓晓 / 任浩铭"
          },
          {
            "timep": "00:04.98",
            "lrcp": "编曲：贺佳豪"
          },
          {
            "timep": "00:05.43",
            "lrcp": "吉他：陈竹 / 蔡勇"
          },
          {
            "timep": "00:05.86",
            "lrcp": "和声：付垚"
          },
          {
            "timep": "00:06.37",
            "lrcp": "混音：路大伟"
          },
          {
            "timep": "00:06.90",
            "lrcp": "录音：祝子由"
          },
          {
            "timep": "00:07.50",
            "lrcp": "制作人：任浩铭/韩俊平"
          },
          {
            "timep": "00:08.12",
            "lrcp": "OP：Leader Music"
          },
          {
            "timep": "00:08.80",
            "lrcp": "发行：百纳娱乐"
          },
          {
            "timep": "00:16.52",
            "lrcp": "男："
          },
          {
            "timep": "00:17.48",
            "lrcp": "听说，最近的你不爱说话"
          },
          {
            "timep": "00:24.49",
            "lrcp": "算了，我也劝自己放下那牵挂"
          },
          {
            "timep": "00:31.49",
            "lrcp": "可是，我没有办法让自己装傻"
          },
          {
            "timep": "00:38.07",
            "lrcp": "我的心，在挣扎"
          },
          {
            "timep": "00:45.35",
            "lrcp": "女："
          },
          {
            "timep": "00:46.08",
            "lrcp": "好了，让自己再平静一下"
          },
          {
            "timep": "00:53.31",
            "lrcp": "走吧，也试着让自己学会放下"
          },
          {
            "timep": "01:00.31",
            "lrcp": "你说，就算我走到海角或天涯"
          },
          {
            "timep": "01:06.80",
            "lrcp": "你都会，陪我回家"
          },
          {
            "timep": "01:13.40",
            "lrcp": "男："
          },
          {
            "timep": "01:14.71",
            "lrcp": "就放开一切去爱吧"
          },
          {
            "timep": "01:18.00",
            "lrcp": "只怪自己太傻太不会表达"
          },
          {
            "timep": "01:21.29",
            "lrcp": "女："
          },
          {
            "timep": "01:21.90",
            "lrcp": "就放开一切去爱吧"
          },
          {
            "timep": "01:25.20",
            "lrcp": "是你让我的心一点一点融化"
          },
          {
            "timep": "01:28.29",
            "lrcp": "男："
          },
          {
            "timep": "01:29.09",
            "lrcp": "就放开一切去爱吧"
          },
          {
            "timep": "01:32.45",
            "lrcp": "从来我不想做爱情的哑巴"
          },
          {
            "timep": "01:35.85",
            "lrcp": "女："
          },
          {
            "timep": "01:36.36",
            "lrcp": "就放开一切去爱吧"
          },
          {
            "timep": "01:39.54",
            "lrcp": "爱对了人一生一世都不害怕"
          },
          {
            "timep": "01:57.65",
            "lrcp": "男："
          },
          {
            "timep": "01:57.89",
            "lrcp": "好了，让自己再平静一下"
          },
          {
            "timep": "02:04.79",
            "lrcp": "走吧，也试着让自己学会放下"
          },
          {
            "timep": "02:10.71",
            "lrcp": "女："
          },
          {
            "timep": "02:12.10",
            "lrcp": "你说，就算我走到海角或天涯"
          },
          {
            "timep": "02:18.46",
            "lrcp": "你都会，陪我回家"
          },
          {
            "timep": "02:25.65",
            "lrcp": "男："
          },
          {
            "timep": "02:26.40",
            "lrcp": "就放开一切去爱吧"
          },
          {
            "timep": "02:29.74",
            "lrcp": "只怪自己太傻太不会表达"
          },
          {
            "timep": "02:33.00",
            "lrcp": "女："
          },
          {
            "timep": "02:33.65",
            "lrcp": "就放开一切去爱吧"
          },
          {
            "timep": "02:36.80",
            "lrcp": "是你让我的心一点一点融化"
          },
          {
            "timep": "02:40.31",
            "lrcp": "男："
          },
          {
            "timep": "02:40.81",
            "lrcp": "就放开一切去爱吧"
          },
          {
            "timep": "02:44.01",
            "lrcp": "从来我不想做爱情的哑巴"
          },
          {
            "timep": "02:47.68",
            "lrcp": "女："
          },
          {
            "timep": "02:48.24",
            "lrcp": "就放开一切去爱吧"
          },
          {
            "timep": "02:51.23",
            "lrcp": "爱对了人一生一世都不害怕"
          },
          {
            "timep": "02:56.37",
            "lrcp": "合："
          },
          {
            "timep": "02:56.65",
            "lrcp": "别再勉强自己"
          },
          {
            "timep": "02:58.30",
            "lrcp": "我不想看到你哭泣"
          },
          {
            "timep": "03:03.51",
            "lrcp": "从来有情人，从来都相信"
          },
          {
            "timep": "03:07.16",
            "lrcp": "从来都会在一起，在一起"
          },
          {
            "timep": "03:13.44",
            "lrcp": "男："
          },
          {
            "timep": "03:14.71",
            "lrcp": "就放开一切去爱吧"
          },
          {
            "timep": "03:18.01",
            "lrcp": "只怪自己太傻太不会表达"
          },
          {
            "timep": "03:20.93",
            "lrcp": "女："
          },
          {
            "timep": "03:21.88",
            "lrcp": "就放开一切去爱吧"
          },
          {
            "timep": "03:25.26",
            "lrcp": "是你让我的心一点一点融化"
          },
          {
            "timep": "03:28.09",
            "lrcp": "男："
          },
          {
            "timep": "03:29.13",
            "lrcp": "就放开一切去爱吧"
          },
          {
            "timep": "03:32.39",
            "lrcp": "从来我不想做爱情的哑巴"
          },
          {
            "timep": "03:35.41",
            "lrcp": "女："
          },
          {
            "timep": "03:36.32",
            "lrcp": "就放开一切去爱吧"
          },
          {
            "timep": "03:39.62",
            "lrcp": "爱对了人一生一世都不害怕"
          }
        ],
        "completed": false,
        "paly": false,
        "share": false
      },
      {
        "id": 11,
        "song": "我愿（电影《白发魔女外传》主题曲）",
        "src": "https://qq632119185.github.io/hook/static/audio/98414.mp3",
        "singer": "王瑞淇",
        "album": "我愿",
        "pic": "http://img.5nd.com/photo/2020album/202011/98414.jpg",
        "lrc": [
          {
            "timep": "00:00.945",
            "lrcp": "我愿（电影《白发魔女外传》主题曲）"
          },
          {
            "timep": "00:01.511",
            "lrcp": "作词：王瑞淇"
          },
          {
            "timep": "00:01.811",
            "lrcp": "作曲：王瑞淇"
          },
          {
            "timep": "00:02.072",
            "lrcp": "演唱：王瑞淇"
          },
          {
            "timep": "00:02.473",
            "lrcp": "制作人：王伊锋"
          },
          {
            "timep": "00:02.863",
            "lrcp": "音乐营销：百态文化"
          },
          {
            "timep": "00:03.359",
            "lrcp": "OP：百态文化"
          },
          {
            "timep": "00:20.150",
            "lrcp": "终究还是难逃 这一场相遇"
          },
          {
            "timep": "00:27.338",
            "lrcp": "我是你降服的天地"
          },
          {
            "timep": "00:34.327",
            "lrcp": "心再也不轻盈 只装得下你"
          },
          {
            "timep": "00:41.072",
            "lrcp": "我是你破除的咒语"
          },
          {
            "timep": "00:47.357",
            "lrcp": "偏偏我是一颗倔强的石头"
          },
          {
            "timep": "00:54.082",
            "lrcp": "卑微到骄傲 笨拙到勇毅"
          },
          {
            "timep": "01:00.750",
            "lrcp": "偏偏我纵身投进你"
          },
          {
            "timep": "01:03.156",
            "lrcp": "深不可测的心底"
          },
          {
            "timep": "01:07.756",
            "lrcp": "我住进四海八荒里"
          },
          {
            "timep": "01:10.998",
            "lrcp": "从此杳无音讯"
          },
          {
            "timep": "01:17.856",
            "lrcp": "我愿是你的耳畔的清风"
          },
          {
            "timep": "01:24.692",
            "lrcp": "陪你听尽世间万代春秋"
          },
          {
            "timep": "01:31.787",
            "lrcp": "我愿是你的杯盏的沽酒"
          },
          {
            "timep": "01:38.440",
            "lrcp": "尝尽百味趁醉意上心头"
          },
          {
            "timep": "02:02.575",
            "lrcp": "偏偏我是一颗倔强的石头"
          },
          {
            "timep": "02:09.266",
            "lrcp": "卑微到骄傲 笨拙到勇毅"
          },
          {
            "timep": "02:16.320",
            "lrcp": "偏偏我纵身投进你"
          },
          {
            "timep": "02:18.717",
            "lrcp": "深不可测的心底"
          },
          {
            "timep": "02:23.089",
            "lrcp": "我住进四海八荒里"
          },
          {
            "timep": "02:26.327",
            "lrcp": "从此杳无音讯"
          },
          {
            "timep": "02:33.552",
            "lrcp": "我愿是你的耳畔的清风"
          },
          {
            "timep": "02:40.061",
            "lrcp": "陪你听尽世间万代春秋"
          },
          {
            "timep": "02:46.946",
            "lrcp": "我愿是你的杯盏的沽酒"
          },
          {
            "timep": "02:53.730",
            "lrcp": "尝尽百味趁醉意上心头"
          },
          {
            "timep": "03:01.391",
            "lrcp": "我愿是你的耳畔的清风"
          },
          {
            "timep": "03:07.631",
            "lrcp": "陪你听尽世间万代春秋"
          },
          {
            "timep": "03:14.736",
            "lrcp": "我愿是你的杯盏的沽酒"
          },
          {
            "timep": "03:21.098",
            "lrcp": "尝尽百味趁醉意上心头"
          },
          {
            "timep": "03:28.393",
            "lrcp": "尝尽百味趁醉意上心头"
          }
        ],
        "completed": false,
        "paly": false,
        "share": false
      },
      {
        "id": 12,
        "song": "夏天",
        "src": "https://qq632119185.github.io/hook/static/audio/98378.mp3",
        "singer": "REN",
        "album": "写给你的歌",
        "pic": "http://img.5nd.com/photo/2020album/202011/98378.jpg",
        "lrc": [
          {
            "timep": "00:00.00",
            "lrcp": "夏天（男生版）-REN"
          },
          {
            "timep": "00:00.44",
            "lrcp": "作词：REN"
          },
          {
            "timep": "00:00.84",
            "lrcp": "作曲：REN"
          },
          {
            "timep": "00:01.29",
            "lrcp": "演唱：REN"
          },
          {
            "timep": "00:01.64",
            "lrcp": "编曲：REN"
          },
          {
            "timep": "00:02.09",
            "lrcp": "和声：赵明慧 @Faye惠惠子/徐睿嫔 @徐小嫔/任颖 @winnie任颖"
          },
          {
            "timep": "00:02.89",
            "lrcp": "混音：刘鸿翥 @Mr_Liu_Studio"
          },
          {
            "timep": "00:03.34",
            "lrcp": "母带：刘鸿翥 @Mr_Liu_Studio"
          },
          {
            "timep": "00:03.80",
            "lrcp": "出品：酌乐艺术 @Joy Art"
          },
          {
            "timep": "00:04.25",
            "lrcp": "统筹：初见文化"
          },
          {
            "timep": "00:04.70",
            "lrcp": "发行：锦州听见音乐文化传媒有限公司"
          },
          {
            "timep": "00:05.10",
            "lrcp": "发行人：王峥儿"
          },
          {
            "timep": "00:38.15",
            "lrcp": "关于这个夏天 我还想挽留一天"
          },
          {
            "timep": "00:45.66",
            "lrcp": "去看看和你一起 一起走过的沙滩"
          },
          {
            "timep": "00:53.57",
            "lrcp": "时间一点点放慢 回忆也渐渐放慢 一瞬间"
          },
          {
            "timep": "01:01.44",
            "lrcp": "我们之间的故事 我不想再说抱歉"
          },
          {
            "timep": "01:07.80",
            "lrcp": "想和你一起 就这样走下去"
          },
          {
            "timep": "01:17.21",
            "lrcp": "时间一点点放慢 风吹淡了那相片 看不见"
          },
          {
            "timep": "01:23.57",
            "lrcp": "在这座城市里 有我们的温暖"
          },
          {
            "timep": "01:33.00",
            "lrcp": "时间一点点放慢 放慢有你的陪伴"
          },
          {
            "timep": "01:41.36",
            "lrcp": "关于这个夏天 我还想挽留一天"
          },
          {
            "timep": "01:48.77",
            "lrcp": "去看看和你一起 一起走过的沙滩"
          },
          {
            "timep": "01:56.73",
            "lrcp": "时间一点点放慢 回忆也渐渐放慢 一瞬间"
          },
          {
            "timep": "02:04.69",
            "lrcp": "我们之间的故事 我不想再说抱歉"
          },
          {
            "timep": "02:23.98",
            "lrcp": "有你的夏天"
          },
          {
            "timep": "02:39.15",
            "lrcp": "有你的陪伴"
          },
          {
            "timep": "02:44.06",
            "lrcp": "关于这个夏天 我还想挽留一天"
          },
          {
            "timep": "02:51.61",
            "lrcp": "去看看和你一起 一起走过的沙滩"
          },
          {
            "timep": "02:59.37",
            "lrcp": "时间一点点放慢 回忆也渐渐放慢 一瞬间"
          },
          {
            "timep": "03:07.28",
            "lrcp": "我们之间的故事 我不想再说抱歉"
          },
          {
            "timep": "03:15.20",
            "lrcp": "我们之间的故事 我不想再说抱歉"
          }
        ],
        "completed": false,
        "paly": false,
        "share": false
      },
      {
        "id": 13,
        "song": "爱是我和你",
        "src": "https://qq632119185.github.io/hook/static/audio/98366.mp3",
        "singer": "文娟",
        "album": "爱是我和你",
        "pic": "http://img.5nd.com/photo/2020album/202011/98366.jpg",
        "lrc": [
          {
            "timep": "00:03.32",
            "lrcp": "爱是我和你"
          },
          {
            "timep": "00:04.85",
            "lrcp": "作词：李志勇"
          },
          {
            "timep": "00:07.90",
            "lrcp": "作曲：李风持"
          },
          {
            "timep": "00:10.85",
            "lrcp": "编曲：张波"
          },
          {
            "timep": "00:13.65",
            "lrcp": "演唱：文娟"
          },
          {
            "timep": "00:15.60",
            "lrcp": "录音混音：喜波"
          },
          {
            "timep": "00:20.14",
            "lrcp": "制作人：李风持"
          },
          {
            "timep": "00:30.35",
            "lrcp": "爱是一朵花"
          },
          {
            "timep": "00:32.30",
            "lrcp": "情是一块泥"
          },
          {
            "timep": "00:37.32",
            "lrcp": "花开在泥土"
          },
          {
            "timep": "00:40.29",
            "lrcp": "堆积的土地"
          },
          {
            "timep": "00:44.51",
            "lrcp": "爱是一道泉"
          },
          {
            "timep": "00:47.26",
            "lrcp": "情是一座山"
          },
          {
            "timep": "00:51.08",
            "lrcp": "泉绕在山间"
          },
          {
            "timep": "00:54.50",
            "lrcp": "从不分离"
          },
          {
            "timep": "00:58.98",
            "lrcp": "爱是一道雷"
          },
          {
            "timep": "01:01.67",
            "lrcp": "情是一道电"
          },
          {
            "timep": "01:05.65",
            "lrcp": "雷在电闪中"
          },
          {
            "timep": "01:09.08",
            "lrcp": "天崩又地裂"
          },
          {
            "timep": "01:12.93",
            "lrcp": "爱是一根缰"
          },
          {
            "timep": "01:16.33",
            "lrcp": "情是一匹马"
          },
          {
            "timep": "01:19.79",
            "lrcp": "缰牵着马去"
          },
          {
            "timep": "01:23.02",
            "lrcp": "肥沃的草原"
          },
          {
            "timep": "01:27.52",
            "lrcp": "情是云和月"
          },
          {
            "timep": "01:30.00",
            "lrcp": "爱是我和你"
          },
          {
            "timep": "01:34.16",
            "lrcp": "云追月"
          },
          {
            "timep": "01:36.60",
            "lrcp": "永远不分离"
          },
          {
            "timep": "01:41.13",
            "lrcp": "情是风和雨"
          },
          {
            "timep": "01:44.03",
            "lrcp": "爱是天和地"
          },
          {
            "timep": "01:48.41",
            "lrcp": "风吹雨"
          },
          {
            "timep": "01:50.98",
            "lrcp": "天地不分离"
          },
          {
            "timep": "02:07.15",
            "lrcp": "爱是一道雷"
          },
          {
            "timep": "02:09.63",
            "lrcp": "情是一道电"
          },
          {
            "timep": "02:13.46",
            "lrcp": "雷在电闪中"
          },
          {
            "timep": "02:17.08",
            "lrcp": "天崩又地裂"
          },
          {
            "timep": "02:20.80",
            "lrcp": "爱是一根缰"
          },
          {
            "timep": "02:24.03",
            "lrcp": "情是一匹马"
          },
          {
            "timep": "02:27.95",
            "lrcp": "缰牵着马去"
          },
          {
            "timep": "02:30.83",
            "lrcp": "肥沃的草原"
          },
          {
            "timep": "02:35.64",
            "lrcp": "情是云和月"
          },
          {
            "timep": "02:38.08",
            "lrcp": "爱是我和你"
          },
          {
            "timep": "02:42.42",
            "lrcp": "云追月"
          },
          {
            "timep": "02:45.12",
            "lrcp": "永远不分离"
          },
          {
            "timep": "02:49.50",
            "lrcp": "情是风和雨"
          },
          {
            "timep": "02:52.10",
            "lrcp": "爱是天和地"
          },
          {
            "timep": "02:56.63",
            "lrcp": "风吹雨"
          },
          {
            "timep": "02:58.98",
            "lrcp": "天地不分离"
          },
          {
            "timep": "03:15.14",
            "lrcp": "情是云和月"
          },
          {
            "timep": "03:17.44",
            "lrcp": "爱是我和你"
          },
          {
            "timep": "03:20.80",
            "lrcp": "云追月"
          },
          {
            "timep": "03:23.75",
            "lrcp": "永远不分离"
          },
          {
            "timep": "03:28.05",
            "lrcp": "情是风和雨"
          },
          {
            "timep": "03:31.41",
            "lrcp": "爱是天和地"
          },
          {
            "timep": "03:36.11",
            "lrcp": "风吹雨"
          },
          {
            "timep": "03:38.64",
            "lrcp": "天地不分离"
          },
          {
            "timep": "03:43.67",
            "lrcp": "风吹雨"
          },
          {
            "timep": "03:45.95",
            "lrcp": "天地不分离"
          }
        ],
        "completed": false,
        "paly": false,
        "share": false
      },
      {
        "id": 14,
        "song": "你是我生命最难忘的歌谣",
        "src": "https://qq632119185.github.io/hook/static/audio/98288.mp3",
        "singer": "曹翟",
        "album": "你是我生命最难忘的歌谣",
        "pic": "http://img.5nd.com/photo/2020album/202010/98288.jpg",
        "lrc": [
          {
            "timep": "00:01.580",
            "lrcp": "你是我生命最难忘的歌谣"
          },
          {
            "timep": "00:03.159",
            "lrcp": "作词：曹翟"
          },
          {
            "timep": "00:04.087",
            "lrcp": "作曲：曹翟 "
          },
          {
            "timep": "00:07.596",
            "lrcp": "编曲：曹翟 "
          },
          {
            "timep": "00:11.105",
            "lrcp": "演唱：曹翟"
          },
          {
            "timep": "00:15.653",
            "lrcp": "发行：杭州回声文化艺术策划有限公司"
          },
          {
            "timep": "00:17.874",
            "lrcp": "天边的夕阳又再次映在我脸上 "
          },
          {
            "timep": "00:24.140",
            "lrcp": "有一群大雁正飞向南方 "
          },
          {
            "timep": "00:31.410",
            "lrcp": "一阵微风吹过带来了你的芬芳 "
          },
          {
            "timep": "00:38.177",
            "lrcp": "沉醉在紫藤花般的幻想 "
          },
          {
            "timep": "00:45.195",
            "lrcp": "后来的我们又经历了多少烦恼 "
          },
          {
            "timep": "00:51.711",
            "lrcp": "多少错过多少怦然心跳 "
          },
          {
            "timep": "00:58.980",
            "lrcp": "梦见有片雪花飘落在你的发梢"
          },
          {
            "timep": "01:05.246",
            "lrcp": "激荡出的旋律我能听得到 "
          },
          {
            "timep": "01:12.265",
            "lrcp": "你是我生命最难忘的一支歌谣 "
          },
          {
            "timep": "01:16.031",
            "lrcp": "在孤独的黑夜里陪着我奔跑 "
          },
          {
            "timep": "01:19.289",
            "lrcp": "从心底流淌在耳畔萦绕 "
          },
          {
            "timep": "01:22.799",
            "lrcp": "看见你温暖的微笑 "
          },
          {
            "timep": "01:26.308",
            "lrcp": "你是我生命最难忘的一支歌谣 "
          },
          {
            "timep": "01:29.817",
            "lrcp": "珍藏在心底永远都不会变老 "
          },
          {
            "timep": "01:33.076",
            "lrcp": "哼唱出纯洁的青春年少 "
          },
          {
            "timep": "01:36.586",
            "lrcp": "也唱出无悔的爱与美好 "
          },
          {
            "timep": "01:57.140",
            "lrcp": "后来的我们又经历了多少烦恼 "
          },
          {
            "timep": "02:03.908",
            "lrcp": "多少错过多少怦然心跳 "
          },
          {
            "timep": "02:10.927",
            "lrcp": "梦见有片雪花飘落在你的发梢"
          },
          {
            "timep": "02:17.695",
            "lrcp": "激荡出的旋律我能听得到"
          },
          {
            "timep": "02:24.713",
            "lrcp": "你是我生命最难忘的一支歌谣 "
          },
          {
            "timep": "02:28.223",
            "lrcp": "在孤独的黑夜里陪着我奔跑 "
          },
          {
            "timep": "02:31.231",
            "lrcp": "从心底流淌在耳畔萦绕 "
          },
          {
            "timep": "02:34.740",
            "lrcp": "看见你温暖的微笑 "
          },
          {
            "timep": "02:38.500",
            "lrcp": "你是我生命最难忘的一支歌谣 "
          },
          {
            "timep": "02:41.759",
            "lrcp": "珍藏在心底永远都不会变老 "
          },
          {
            "timep": "02:45.268",
            "lrcp": "哼唱出纯洁的青春年少 "
          },
          {
            "timep": "02:48.527",
            "lrcp": "也唱出无悔的爱 "
          },
          {
            "timep": "02:52.036",
            "lrcp": "你是我生命最难忘的一支歌谣 "
          },
          {
            "timep": "02:55.545",
            "lrcp": "在孤独的黑夜里陪着我奔跑 "
          },
          {
            "timep": "02:59.055",
            "lrcp": "从心底流淌在耳畔萦绕 "
          },
          {
            "timep": "03:02.313",
            "lrcp": "看见你温暖的微笑 "
          },
          {
            "timep": "03:05.823",
            "lrcp": "你是我生命最难忘的一支歌谣 "
          },
          {
            "timep": "03:09.332",
            "lrcp": "珍藏在心底永远都不会变老 "
          },
          {
            "timep": "03:12.842",
            "lrcp": "哼唱出纯洁的青春年少 "
          },
          {
            "timep": "03:16.351",
            "lrcp": "也唱出无悔的爱与美好"
          },
          {
            "timep": "03:18.351",
            "lrcp": "也唱出无悔的爱与美好"
          }
        ],
        "completed": false,
        "paly": false,
        "share": false
      }
    ]
}